[
	{
		"slug": "space-cookie",
		"name": "Mad Max",
		"image": "mad-max-01.png",
		"tags": ["Mad Max"]
	},
	{
		"name": "Mad Max",
		"image": "mad-max-02.png",
		"tags": ["Mad Max"]
    },
    {
		"name": "Mad Max",
		"image": "mad-max-03.png",
		"tags": ["Mad Max"]
    },
    {
		"name": "Mad Max",
		"image": "mad-max-04.png",
		"tags": ["Mad Max"]
    },
    {
		"name": "Mad Max",
		"image": "mad-max-05.png",
		"tags": ["Mad Max"]
    },
    {
		"name": "Mad Max",
		"image": "mad-max-06.png",
		"tags": ["Mad Max"]
	}

]